ceryle/__init__.py
ceryle/__main__.py
ceryle/const.py
ceryle/main.py
ceryle/commands/__init__.py
ceryle/commands/builtin.py
ceryle/commands/command.py
ceryle/commands/copy.py
ceryle/commands/executable.py
ceryle/commands/remove.py
ceryle/dsl/__init__.py
ceryle/dsl/aggregate_loader.py
ceryle/dsl/loader.py
ceryle/dsl/parser.py
ceryle/dsl/support.py
ceryle/tasks/__init__.py
ceryle/tasks/condition.py
ceryle/tasks/resolver.py
ceryle/tasks/runner.py
ceryle/tasks/task.py
ceryle/util/__init__.py
ceryle/util/assertions.py
ceryle/util/capture.py
ceryle/util/functions.py
ceryle/util/platform.py
ceryle/util/printutils.py
ceryle/util/time.py
ceryle-0.4.1.dist-info/LICENSE
ceryle-0.4.1.dist-info/METADATA
ceryle-0.4.1.dist-info/WHEEL
ceryle-0.4.1.dist-info/entry_points.txt
ceryle-0.4.1.dist-info/top_level.txt
ceryle-0.4.1.dist-info/RECORD
