Metadata-Version: 2.1
Name: ceryle
Version: 0.4.1
Summary: Task based command runner tool
Home-page: https://github.com/kikuchi-m/ceryle
Author: Kikuchi Motoki
Author-email: wildflower.pink0102@gmail.com
License: MIT
Platform: UNKNOWN
Classifier: Development Status :: 3 - Alpha
Classifier: Environment :: Console
Classifier: Intended Audience :: Developers
Requires-Python: >=3.6.5
